cluster_depp_test-0.0.21.data/scripts/agg_dist.py
cluster_depp_test-0.0.21.data/scripts/comb_json.py
cluster_depp_test-0.0.21.data/scripts/count_gapped_ratio.py
cluster_depp_test-0.0.21.data/scripts/depp-place-rRNA-one-type.sh
cluster_depp_test-0.0.21.data/scripts/depp-place-rRNA.sh
cluster_depp_test-0.0.21.data/scripts/depp_distance.py
cluster_depp_test-0.0.21.data/scripts/filter_by_entropy_gap.sh
cluster_depp_test-0.0.21.data/scripts/get_names_by_entropy_gap.py
cluster_depp_test-0.0.21.data/scripts/grep_jplace.py
cluster_depp_test-0.0.21.data/scripts/grep_seq.py
cluster_depp_test-0.0.21.data/scripts/merge_json.py
cluster_depp_test-0.0.21.data/scripts/run_upp.sh
cluster_depp_test-0.0.21.data/scripts/seq_sep.py
cluster_depp_test-0.0.21.data/scripts/train_depp.py
cluster_depp_test-0.0.21.data/scripts/train_depp_recon.py
cluster_depp_test-0.0.21.data/scripts/wol_placement.sh
depp/Agg_model.py
depp/Model_pl.py
depp/Model_recon.py
depp/__init__.py
depp/count_gapped_ratio.py
depp/data.py
depp/data.split.py
depp/data_recon.py
depp/default_config.py
depp/depp_distance.py
depp/filter_by_entropy_gap.sh
depp/get_names_by_entropy_gap.py
depp/grep_jplace.py
depp/grep_seq.py
depp/submodule.py
depp/utils.py
cluster_depp_test-0.0.21.dist-info/METADATA
cluster_depp_test-0.0.21.dist-info/WHEEL
cluster_depp_test-0.0.21.dist-info/top_level.txt
cluster_depp_test-0.0.21.dist-info/RECORD
